<?xml version="1.0" encoding="utf-8"?>
<Defs>

  <SitePartDef>
    <defName>BlackMarketOutpost</defName>
    <label>black market outpost</label>
    <description>A hidden black market den. It will expire in time. Until then, you can raid it if you wish.</description>
    <workerClass>MiningOutpost.SitePartWorker_ExpandedOutpost</workerClass>
    <siteTexture>World/WorldObjects/Sites/Outpost</siteTexture>
    <expandingIconTexture>World/WorldObjects/Sites/WorkSite</expandingIconTexture>
    <applyFactionColorToSiteTexture>true</applyFactionColorToSiteTexture>
    <showFactionInInspectString>true</showFactionInInspectString>
    <requiresFaction>true</requiresFaction>
    <considerEnteringAsAttack>true</considerEnteringAsAttack>
    <gravShipsCanLandOn>true</gravShipsCanLandOn>
    <approachOrderString>Attack {0}</approachOrderString>
    <approachingReportString>Attacking {0}.</approachingReportString>
    <wantsThreatPoints>true</wantsThreatPoints>
    <minThreatPoints>350</minThreatPoints>
    <tags>
      <li>BlackMarketOutpost</li>
    </tags>
  </SitePartDef>

</Defs>
